minnwest_esb_client_q2/__init__.py
minnwest_esb_client_q2/api/__init__.py
minnwest_esb_client_q2/api/account/__init__.py
minnwest_esb_client_q2/api/account/post_api_v_1_q_2_account_view_reward_accounts.py
minnwest_esb_client_q2/api/account/post_api_v_1_q_2_account_view_transfers.py
minnwest_esb_client_q2/api/auth/__init__.py
minnwest_esb_client_q2/api/auth/get_api_v_1_q_2_auth_check.py
minnwest_esb_client_q2/api/auth/post_api_v_1_q_2_auth_login.py
minnwest_esb_client_q2/api/auth/post_api_v_1_q_2_auth_refresh.py
minnwest_esb_client_q2/api/config/__init__.py
minnwest_esb_client_q2/api/config/get_api_v_1_q_2_config.py
minnwest_esb_client_q2/api/enrollment/__init__.py
minnwest_esb_client_q2/api/enrollment/post_api_v_1_q_2_enrollment_view_enrollment.py
minnwest_esb_client_q2/api/log/__init__.py
minnwest_esb_client_q2/api/log/post_api_v_1_q_2_log_change_email.py
minnwest_esb_client_q2/api/names/__init__.py
minnwest_esb_client_q2/api/names/post_api_v_1_q_2_names_get_name.py
minnwest_esb_client_q2/api/names/post_api_v_1_q_2_names_update_email.py
minnwest_esb_client_q2/api/portfolio/__init__.py
minnwest_esb_client_q2/api/portfolio/post_api_v_1_q_2_portfolio_view_transfers.py
minnwest_esb_client_q2/api/transfers/__init__.py
minnwest_esb_client_q2/api/transfers/post_api_v_1_q_2_transfers_internal.py
minnwest_esb_client_q2/client.py
minnwest_esb_client_q2/errors.py
minnwest_esb_client_q2/models/__init__.py
minnwest_esb_client_q2/models/account_application_type.py
minnwest_esb_client_q2/models/account_transfer_view_request.py
minnwest_esb_client_q2/models/account_type.py
minnwest_esb_client_q2/models/application_dto.py
minnwest_esb_client_q2/models/application_dto_api_result.py
minnwest_esb_client_q2/models/application_setting_dto.py
minnwest_esb_client_q2/models/base_account_mapping.py
minnwest_esb_client_q2/models/boolean_api_result.py
minnwest_esb_client_q2/models/customer_address.py
minnwest_esb_client_q2/models/customer_contact_data.py
minnwest_esb_client_q2-3.4.0.dist-info/METADATA
minnwest_esb_client_q2-3.4.0.dist-info/WHEEL
minnwest_esb_client_q2-3.4.0.dist-info/RECORD
